{
    "/vue/js/app.js": "/vue/js/app.js",
    "/vue/css/app.css": "/vue/css/app.css",
    "/0.d5b046e775e651c5b5a4.hot-update.js": "/0.d5b046e775e651c5b5a4.hot-update.js",
    "/0.00bd4329034ad8b60e94.hot-update.js": "/0.00bd4329034ad8b60e94.hot-update.js",
    "/0.01cb545fe2843b7f5106.hot-update.js": "/0.01cb545fe2843b7f5106.hot-update.js",
    "/0.6b928269a3ba8f4e37cf.hot-update.js": "/0.6b928269a3ba8f4e37cf.hot-update.js",
    "/0.6ed6a05ede2570d6f991.hot-update.js": "/0.6ed6a05ede2570d6f991.hot-update.js",
    "/0.e334509fb3fa2f3c9506.hot-update.js": "/0.e334509fb3fa2f3c9506.hot-update.js",
    "/0.ae0dca65ca92f129121b.hot-update.js": "/0.ae0dca65ca92f129121b.hot-update.js",
    "/0.05bc0eeb6637a23c15be.hot-update.js": "/0.05bc0eeb6637a23c15be.hot-update.js",
    "/0.2ad532bd868dc15300e1.hot-update.js": "/0.2ad532bd868dc15300e1.hot-update.js",
    "/0.f6ae1032199f31d04413.hot-update.js": "/0.f6ae1032199f31d04413.hot-update.js",
    "/0.208d417ea257b928f711.hot-update.js": "/0.208d417ea257b928f711.hot-update.js",
    "/0.38a8dd53865165394ad1.hot-update.js": "/0.38a8dd53865165394ad1.hot-update.js",
    "/0.ebab2756618216108c7c.hot-update.js": "/0.ebab2756618216108c7c.hot-update.js",
    "/0.ee8ee93f42ed31227fbc.hot-update.js": "/0.ee8ee93f42ed31227fbc.hot-update.js",
    "/0.44cf481526c5fc3b275d.hot-update.js": "/0.44cf481526c5fc3b275d.hot-update.js",
    "/0.c0e3b2cd1689dc6ce025.hot-update.js": "/0.c0e3b2cd1689dc6ce025.hot-update.js",
    "/0.7525ccb883c4fcbff2e9.hot-update.js": "/0.7525ccb883c4fcbff2e9.hot-update.js",
    "/0.78fc7e5b2d9409148076.hot-update.js": "/0.78fc7e5b2d9409148076.hot-update.js",
    "/0.bcb97cd6bc86e7d0da03.hot-update.js": "/0.bcb97cd6bc86e7d0da03.hot-update.js",
    "/0.e49357f0bf4b7c3635b6.hot-update.js": "/0.e49357f0bf4b7c3635b6.hot-update.js",
    "/0.5545fea300af33a5decb.hot-update.js": "/0.5545fea300af33a5decb.hot-update.js",
    "/0.ec9f461a160607d9116a.hot-update.js": "/0.ec9f461a160607d9116a.hot-update.js",
    "/0.ac4df5d8595d0d27bfb0.hot-update.js": "/0.ac4df5d8595d0d27bfb0.hot-update.js",
    "/0.1e209623ed431a47d6e3.hot-update.js": "/0.1e209623ed431a47d6e3.hot-update.js",
    "/0.c117b0e77fcce777343d.hot-update.js": "/0.c117b0e77fcce777343d.hot-update.js",
    "/0.c39a609cb52c82967507.hot-update.js": "/0.c39a609cb52c82967507.hot-update.js",
    "/0.6664679655e6bd4e86ba.hot-update.js": "/0.6664679655e6bd4e86ba.hot-update.js",
    "/0.1c2a58f623547d5e2845.hot-update.js": "/0.1c2a58f623547d5e2845.hot-update.js",
    "/0.f21b4ad959f90dfb7afe.hot-update.js": "/0.f21b4ad959f90dfb7afe.hot-update.js",
    "/0.0a76e08205a32a49ac40.hot-update.js": "/0.0a76e08205a32a49ac40.hot-update.js",
    "/0.264c72a96b5d20ff973b.hot-update.js": "/0.264c72a96b5d20ff973b.hot-update.js",
    "/0.aa6d1ba8afdd1eff2fe1.hot-update.js": "/0.aa6d1ba8afdd1eff2fe1.hot-update.js",
    "/0.3f7ead1a090b78220845.hot-update.js": "/0.3f7ead1a090b78220845.hot-update.js",
    "/0.cca410feed5c5d1fae23.hot-update.js": "/0.cca410feed5c5d1fae23.hot-update.js",
    "/0.542f1f4883661e05c3b2.hot-update.js": "/0.542f1f4883661e05c3b2.hot-update.js",
    "/0.da86e6d789344cc7eb1f.hot-update.js": "/0.da86e6d789344cc7eb1f.hot-update.js",
    "/0.3974b9d68b1e1e12e37d.hot-update.js": "/0.3974b9d68b1e1e12e37d.hot-update.js",
    "/0.5efda1edb63e5f4ea13c.hot-update.js": "/0.5efda1edb63e5f4ea13c.hot-update.js",
    "/0.d56f1b5e2e314ac82bb2.hot-update.js": "/0.d56f1b5e2e314ac82bb2.hot-update.js",
    "/0.6cbb6806e01a8f79f51c.hot-update.js": "/0.6cbb6806e01a8f79f51c.hot-update.js",
    "/0.4dcb820aaf6274622bb1.hot-update.js": "/0.4dcb820aaf6274622bb1.hot-update.js",
    "/0.b4e9b66cb377765dc704.hot-update.js": "/0.b4e9b66cb377765dc704.hot-update.js",
    "/0.0e61e124f0803ce2108f.hot-update.js": "/0.0e61e124f0803ce2108f.hot-update.js",
    "/0.9e3c3ee777eee0c07ffb.hot-update.js": "/0.9e3c3ee777eee0c07ffb.hot-update.js",
    "/0.f1a9c6a983c743f79dc7.hot-update.js": "/0.f1a9c6a983c743f79dc7.hot-update.js",
    "/0.0f104e9082d365c6fcd3.hot-update.js": "/0.0f104e9082d365c6fcd3.hot-update.js",
    "/0.bea892b9dcc5c6353d6e.hot-update.js": "/0.bea892b9dcc5c6353d6e.hot-update.js",
    "/0.97de6097e0d376f812f9.hot-update.js": "/0.97de6097e0d376f812f9.hot-update.js",
    "/0.2b7c458157788012a7be.hot-update.js": "/0.2b7c458157788012a7be.hot-update.js",
    "/0.37487f736ca0686bbc83.hot-update.js": "/0.37487f736ca0686bbc83.hot-update.js",
    "/0.db439fddaeb012dcc18a.hot-update.js": "/0.db439fddaeb012dcc18a.hot-update.js"
}